{
  "version": "0.1.16",
  "updateTime": 1683925691,
  "history": {
    "user": [
      {
        "name": "tourist",
        "newSubmissions": [
          {
            "platform": "codeforces",
            "id": 205596162,
            "pid": "1832F",
            "name": "Zombies",
            "verdict": "OK",
            "creationTime": 1683906205
          },
          {
            "platform": "codeforces",
            "id": 205595830,
            "pid": "1832F",
            "name": "Zombies",
            "verdict": "MEMORY_LIMIT_EXCEEDED",
            "creationTime": 1683906156
          },
          {
            "platform": "codeforces",
            "id": 205573248,
            "pid": "1832D2",
            "name": "Red-Blue Operations (Hard Version)",
            "verdict": "OK",
            "creationTime": 1683903721
          },
          {
            "platform": "codeforces",
            "id": 205565935,
            "pid": "1832D1",
            "name": "Red-Blue Operations (Easy Version)",
            "verdict": "OK",
            "creationTime": 1683903129
          },
          {
            "platform": "codeforces",
            "id": 205562791,
            "pid": "1832E",
            "name": "Combinatorics Problem",
            "verdict": "OK",
            "creationTime": 1683902908
          },
          {
            "platform": "codeforces",
            "id": 205552484,
            "pid": "1832C",
            "name": "Contrast Value",
            "verdict": "OK",
            "creationTime": 1683902362
          },
          {
            "platform": "codeforces",
            "id": 205549640,
            "pid": "1832B",
            "name": "Maximum Sum",
            "verdict": "OK",
            "creationTime": 1683902256
          },
          {
            "platform": "codeforces",
            "id": 205548635,
            "pid": "1832A",
            "name": "New Palindrome",
            "verdict": "OK",
            "creationTime": 1683902184
          }
        ],
        "newContests": []
      }
    ],
    "contest": []
  },
  "ref": "25ee20de4749c939ddf7d5b6af17c3a97c5159b0"
}