{
  "version": "0.1.16",
  "updateTime": 1652044219,
  "history": {
    "user": [
      {
        "name": "tourist",
        "newSubmissions": [
          {
            "platform": "codeforces",
            "id": 156323238,
            "pid": "1677D",
            "name": "Tokitsukaze and Permutations",
            "verdict": "OK",
            "creationTime": 1652023201
          },
          {
            "platform": "codeforces",
            "id": 156318644,
            "pid": "1677E",
            "name": "Tokitsukaze and Beautiful Subsegments",
            "verdict": "OK",
            "creationTime": 1652022591
          },
          {
            "platform": "codeforces",
            "id": 156302984,
            "pid": "1677C",
            "name": "Tokitsukaze and Two Colorful Tapes",
            "verdict": "OK",
            "creationTime": 1652021132
          },
          {
            "platform": "codeforces",
            "id": 156299817,
            "pid": "1677B",
            "name": "Tokitsukaze and Meeting",
            "verdict": "OK",
            "creationTime": 1652020930
          },
          {
            "platform": "codeforces",
            "id": 156295896,
            "pid": "1677A",
            "name": "Tokitsukaze and Strange Inequality",
            "verdict": "OK",
            "creationTime": 1652020617
          }
        ],
        "newContests": []
      }
    ],
    "contest": []
  },
  "ref": "b13f79e559733f82bac2311bc68ec5636499d8e7"
}