{
  "version": "0.1.16",
  "updateTime": 1666473145,
  "history": {
    "user": [
      {
        "name": "陈陆洋",
        "newSubmissions": [
          {
            "platform": "codeforces",
            "id": 177376426,
            "pid": "1654E",
            "name": "Arithmetic Operations",
            "verdict": "OK",
            "creationTime": 1666397617
          },
          {
            "platform": "codeforces",
            "id": 177376412,
            "pid": "1654E",
            "name": "Arithmetic Operations",
            "verdict": "OK",
            "creationTime": 1666397574
          },
          {
            "platform": "codeforces",
            "id": 177376356,
            "pid": "1654E",
            "name": "Arithmetic Operations",
            "verdict": "RUNTIME_ERROR",
            "creationTime": 1666397444
          },
          {
            "platform": "codeforces",
            "id": 177376207,
            "pid": "1654E",
            "name": "Arithmetic Operations",
            "verdict": "TIME_LIMIT_EXCEEDED",
            "creationTime": 1666397051
          },
          {
            "platform": "codeforces",
            "id": 177376148,
            "pid": "1654E",
            "name": "Arithmetic Operations",
            "verdict": "TIME_LIMIT_EXCEEDED",
            "creationTime": 1666396936
          }
        ],
        "newContests": []
      }
    ],
    "contest": []
  },
  "ref": "e5e6810861cbc4122c419d6207d008628272014b"
}