{
  "version": "0.1.16",
  "updateTime": 1649624985,
  "history": {
    "user": [
      {
        "name": "陈陆洋",
        "newSubmissions": [
          {
            "platform": "codeforces",
            "id": 153254616,
            "pid": "1257E",
            "name": "The Contest",
            "verdict": "OK",
            "creationTime": 1649561947
          },
          {
            "platform": "codeforces",
            "id": 153246594,
            "pid": "1257E",
            "name": "The Contest",
            "verdict": "OK",
            "creationTime": 1649547836
          },
          {
            "platform": "codeforces",
            "id": 153245993,
            "pid": "1257E",
            "name": "The Contest",
            "verdict": "WRONG_ANSWER",
            "creationTime": 1649546534
          },
          {
            "platform": "codeforces",
            "id": 153245890,
            "pid": "1257E",
            "name": "The Contest",
            "verdict": "WRONG_ANSWER",
            "creationTime": 1649546318
          }
        ],
        "newContests": []
      }
    ],
    "contest": []
  },
  "ref": "3fdfbe16b2ec5a844fbeb5ce9303114b6230feac"
}