{
  "version": "0.1.16",
  "updateTime": 1643663328,
  "history": {
    "user": [
      {
        "name": "然然",
        "newSubmissions": [
          {
            "platform": "codeforces",
            "id": 144624109,
            "pid": "1632D",
            "name": "New Year Concert",
            "verdict": "OK",
            "creationTime": 1643613623
          }
        ],
        "newContests": []
      },
      {
        "name": "陈陆洋",
        "newSubmissions": [
          {
            "platform": "codeforces",
            "id": 144716819,
            "pid": "1633D",
            "name": "Make Them Equal",
            "verdict": "OK",
            "creationTime": 1643643082
          },
          {
            "platform": "codeforces",
            "id": 144711190,
            "pid": "1633D",
            "name": "Make Them Equal",
            "verdict": "WRONG_ANSWER",
            "creationTime": 1643642612
          },
          {
            "platform": "codeforces",
            "id": 144706421,
            "pid": "1633D",
            "name": "Make Them Equal",
            "verdict": "WRONG_ANSWER",
            "creationTime": 1643642253
          },
          {
            "platform": "codeforces",
            "id": 144686981,
            "pid": "1633C",
            "name": "Kill the Monster",
            "verdict": "OK",
            "creationTime": 1643641067
          },
          {
            "platform": "codeforces",
            "id": 144685793,
            "pid": "1633C",
            "name": "Kill the Monster",
            "verdict": "WRONG_ANSWER",
            "creationTime": 1643641008
          },
          {
            "platform": "codeforces",
            "id": 144670050,
            "pid": "1633B",
            "name": "Minority",
            "verdict": "OK",
            "creationTime": 1643640355
          },
          {
            "platform": "codeforces",
            "id": 144659696,
            "pid": "1633A",
            "name": "Div. 7",
            "verdict": "OK",
            "creationTime": 1643639968
          },
          {
            "platform": "codeforces",
            "id": 144633137,
            "pid": "1624D",
            "name": "Palindromes Coloring",
            "verdict": "OK",
            "creationTime": 1643621355
          },
          {
            "platform": "codeforces",
            "id": 144627681,
            "pid": "1624C",
            "name": "Division by Two and Permutation",
            "verdict": "OK",
            "creationTime": 1643616699
          },
          {
            "platform": "codeforces",
            "id": 144627600,
            "pid": "1624C",
            "name": "Division by Two and Permutation",
            "verdict": "OK",
            "creationTime": 1643616625
          },
          {
            "platform": "codeforces",
            "id": 144608674,
            "pid": "1624B",
            "name": "Make AP",
            "verdict": "OK",
            "creationTime": 1643599757
          },
          {
            "platform": "codeforces",
            "id": 144608653,
            "pid": "1624B",
            "name": "Make AP",
            "verdict": "OK",
            "creationTime": 1643599717
          },
          {
            "platform": "codeforces",
            "id": 144608599,
            "pid": "1624B",
            "name": "Make AP",
            "verdict": "WRONG_ANSWER",
            "creationTime": 1643599632
          },
          {
            "platform": "codeforces",
            "id": 144607906,
            "pid": "1624A",
            "name": "Plus One on the Subset",
            "verdict": "OK",
            "creationTime": 1643598429
          }
        ],
        "newContests": []
      }
    ],
    "contest": []
  },
  "ref": "eb7d6dec3838e3e4b4b51b0805d8d4ade3e48e3d"
}